[
    {
        "ID": 1,
        "Product URL": "https://www.amazon.de/dp/000004458X",
        "Product Title": "Old Spice Shaving Cream - 70 g (original) - Pack of 2",
        "Product Image URL": "https://images-eu.ssl-images-amazon.com/images/I/41xHbjdSXJL._SY300_SX300_QL70_ML2_.jpg",
        "Price of the Product": "\u20ac8.00",
        "Product Details": " Old Spice Shaving Cream - 70g (Original) - Pack of 2 - Good lubrication quality in Old Spice Lather shaving foam gives optimal gliding action a tighter, comfortable shave. Richer, longer - lasting foam stays on during your shave. Use Old Spice Lather shaving cream where you will find the masculine freshness of the old spice. "
    },
    {
        "ID": 2,
        "Product URL": "https://www.amazon.de/dp/000101742X",
        "Product Title": "Short Story: Violoncello und Klavier. (Cello-Bibliothek)",
        "Product Image URL": "https://images-eu.ssl-images-amazon.com/images/I/41zw0783tpL._SX198_BO1,204,203,200_QL40_ML2_.jpg",
        "Price of the Product": "\u20ac16.00",
        "Product Details": "Product detailsPublisher  : SCHOTT MUSIC GmbH & Co KG, Mainz (6 Feb. 1986) Language  : French Sheet music  : 10 pages ISBN-10  : 000101742X ISBN-13  : 978-0001017429"
    },
    {
        "ID": 3,
        "Product URL": "https://www.amazon.fr/dp/000101742X",
        "Product Title": "Short story (dushkin/hegyi) violon",
        "Product Image URL": "https://images-eu.ssl-images-amazon.com/images/I/41zw0783tpL._SX218_BO1,204,203,200_QL40_ML2_.jpg",
        "Price of the Product": "(0%)",
        "Product Details": "Dtails sur le produitditeur : SCHOTT (1 janvier 2000) Langue : Franais ISBN-10 : 000101742X ISBN-13 : 978-0001017429 Poids de l'article : 601 g"
    },
    {
        "ID": 4,
        "Product URL": "https://www.amazon.de/dp/000102163X",
        "Product Title": "Concerto grosso g-Moll: Weihnachtskonzert. op. 6/8. 2 Violinen, Violoncello, Streichorchester und Cembalo. Partitur. (Concertino)",
        "Product Image URL": "https://images-eu.ssl-images-amazon.com/images/I/51sNFyf2t6L._SX198_BO1,204,203,200_QL40_ML2_.jpg",
        "Price of the Product": "(0%)",
        "Product Details": "Product detailsPublisher  : SCHOTT MUSIC GmbH & Co KG, Mainz (24 Feb. 1984) Language  : French Sheet music  : 30 pages ISBN-10  : 000102163X ISBN-13  : 978-0001021631 Best Sellers Rank:2,425,576 in Books (See Top 100 in Books) 4,031 in Strings Songbooks5,635 in Piano & Keyboards Songbooks24,055 in Piano, Vocal & Guitar Songbooks"
    },
    {
        "ID": 5,
        "Product URL": "https://www.amazon.fr/dp/000102163X",
        "Product Title": "Concerto grosso 8 g opus 6 partitu",
        "Product Image URL": "https://images-eu.ssl-images-amazon.com/images/I/51sNFyf2t6L._SX218_BO1,204,203,200_QL40_ML2_.jpg",
        "Price of the Product": "(0%)",
        "Product Details": "Dtails sur le produitditeur : SCHOTT (1 janvier 2000) Langue : Franais ISBN-10 : 000102163X ISBN-13 : 978-0001021631 Poids de l'article : 358 g"
    },
    {
        "ID": 6,
        "Product URL": "https://www.amazon.de/dp/000103863X",
        "Product Title": "Concertino B-Dur: Violine und Orchester. Klavierauszug mit Solostimme. (Edition Schott)",
        "Product Image URL": "https://images-eu.ssl-images-amazon.com/images/I/41HnYQBk7PL._SX198_BO1,204,203,200_QL40_ML2_.jpg",
        "Price of the Product": "(0%)",
        "Product Details": "Product detailsPublisher  : SCHOTT MUSIC GmbH & Co KG, Mainz (18 Jan. 1980) Language  : French Sheet music  : 28 pages ISBN-10  : 000103863X ISBN-13  : 979-0001038638 Best Sellers Rank:5,018,688 in Books (See Top 100 in Books) 6,850 in Strings Songbooks43,804 in Piano, Vocal & Guitar Songbooks3,500,860 in Foreign Language Books"
    },
    {
        "ID": 7,
        "Product URL": "https://www.amazon.fr/dp/000103863X",
        "Product Title": "Concertino bes violon",
        "Product Image URL": "https://images-eu.ssl-images-amazon.com/images/I/41HnYQBk7PL._SX218_BO1,204,203,200_QL40_ML2_.jpg",
        "Price of the Product": "(0%)",
        "Product Details": "Dtails sur le produitditeur : SCHOTT (1 janvier 2000) Langue : Franais ISBN-10 : 000103863X ISBN-13 : 979-0001038638 Poids de l'article : 701 g"
    },
    {
        "ID": 8,
        "Product URL": "https://www.amazon.de/dp/000104317X",
        "Product Title": "Concerto in E flat \"Dumbarton Oaks\": f\u00fcr Kammerorchester. Kammerorchester. Studienpartitur. (Musik unserer Zeit)",
        "Product Image URL": "https://images-eu.ssl-images-amazon.com/images/I/41fgZjPnmCL._SY264_BO1,204,203,200_QL40_ML2_.jpg",
        "Price of the Product": "\u20ac18.00",
        "Product Details": "Product detailsPublisher  : SCHOTT MUSIC GmbH & Co KG, Mainz; Das exakte Erscheinungsdatum ist leider unbekannt edition (19 July 1984) Language  : French Sheet music  : 44 pages ISBN-10  : 000104317X ISBN-13  : 978-0001043176 Best Sellers Rank:878,935 in Books (See Top 100 in Books) 7,765 in Piano, Vocal & Guitar Songbooks410,767 in Foreign Language Books"
    },
    {
        "ID": 9,
        "Product URL": "https://www.amazon.fr/dp/000104317X",
        "Product Title": "Concert es kammerorchester parti musique d'ensemble",
        "Product Image URL": "https://images-eu.ssl-images-amazon.com/images/I/41fgZjPnmCL._SY291_BO1,204,203,200_QL40_ML2_.jpg",
        "Price of the Product": "27,08\u00a0\u20ac",
        "Product Details": "Dtails sur le produitditeur : SCHOTT (1 janvier 2000) Langue : Franais ISBN-10 : 000104317X ISBN-13 : 978-0001043176 Poids de l'article : 601 g Classement des meilleures ventes d'Amazon :1,840,314 en Livres (Voir les 100 premiers en Livres) 1,674 en Partitions musicales pour l'orchestre et groupes"
    },
    {
        "ID": 10,
        "Product URL": "https://www.amazon.de/dp/000104348X",
        "Product Title": "Musik f\u00fcr Kinder: Im F\u00fcnftonraum. Vol. 1. Singstimme, Blockfl\u00f6te und Schlagzeug. Sing- und Spielpartitur. (Orff-Schulwerk)",
        "Product Image URL": "https://images-eu.ssl-images-amazon.com/images/I/419-3yqvVML._SX198_BO1,204,203,200_QL40_ML2_.jpg",
        "Price of the Product": "0% (0%)",
        "Product Details": "Product detailsPublisher  : SCHOTT MUSIC GmbH & Co KG, Mainz (21 April 1980) Language  : German Sheet music  : 187 pages ISBN-10  : 000104348X ISBN-13  : 978-0001043480 Best Sellers Rank:1,839,790 in Books (See Top 100 in Books) 517 in Percussion Songbooks2,009 in Vocal Songbooks17,981 in Piano, Vocal & Guitar Songbooks Customer reviews:5.0 out of 5 stars 1 rating"
    },
    {
        "ID": 11,
        "Product URL": "https://www.amazon.fr/dp/000104348X",
        "Product Title": "Schulwerk vol. 1 (ted.) (orff/keetman)",
        "Product Image URL": "https://images-eu.ssl-images-amazon.com/images/I/419-3yqvVML._SX218_BO1,204,203,200_QL40_ML2_.jpg",
        "Price of the Product": "0% (0%)",
        "Product Details": "Dtails sur le produitditeur : SCHOTT (1 janvier 2000) Langue : Allemand ISBN-10 : 000104348X ISBN-13 : 978-0001043480 Poids de l'article : 701 g Commentaires client:5,0 sur 5toiles 1 valuation"
    },
    {
        "ID": 12,
        "Product URL": "https://www.amazon.de/dp/000104396X",
        "Product Title": "5 antike Oden: nach Gedichten von Sappho. op. 57. mittlere Frauenstimme, Viola und Klavier. mittel. Stimmensatz. (Edition Schott)",
        "Product Image URL": "https://images-eu.ssl-images-amazon.com/images/I/41uGG66YO-L._SX198_BO1,204,203,200_QL40_ML2_.jpg",
        "Price of the Product": "\u20ac32.00",
        "Product Details": "Product detailsPublisher  : SCHOTT MUSIC GmbH & Co KG, Mainz (7 May 1985) Language  : German Sheet music  : 32 pages ISBN-10  : 000104396X ISBN-13  : 978-0001043961"
    },
    {
        "ID": 13,
        "Product URL": "https://www.amazon.fr/dp/000104396X",
        "Product Title": "Funf antike oden op. 57 -ensemble de partitions",
        "Product Image URL": "https://images-eu.ssl-images-amazon.com/images/I/41uGG66YO-L._SX218_BO1,204,203,200_QL40_ML2_.jpg",
        "Price of the Product": "(0%)",
        "Product Details": "Dtails sur le produitditeur : SCHOTT (1 janvier 1985) Langue : Allemand ISBN-10 : 000104396X ISBN-13 : 978-0001043961 Poids de l'article : 1 kg"
    },
    {
        "ID": 14,
        "Product URL": "https://www.amazon.es/dp/000106875X",
        "Product Title": "Etuden 1 & 2 orgue",
        "Product Image URL": "https://images-na.ssl-images-amazon.com/images/I/31+SH2b7VAL._SX258_BO1,204,203,200_.jpg",
        "Price of the Product": "31,19\u00a0\u20ac",
        "Product Details": "Detalles del productoEditorial  : SCHOTT (1 enero 2000) Idioma  : Francs ISBN-10  : 000106875X ISBN-13  : 978-0001068759 Peso del producto  : 701 g"
    },
    {
        "ID": 15,
        "Product URL": "https://www.amazon.fr/dp/000106875X",
        "Product Title": "Etuden 1 & 2 orgue",
        "Product Image URL": "https://images-na.ssl-images-amazon.com/images/I/31+SH2b7VAL._SX258_BO1,204,203,200_.jpg",
        "Price of the Product": "31,19\u00a0\u20ac",
        "Product Details": "Dtails sur le produitditeur : SCHOTT (1 janvier 2000) Langue : Franais ISBN-10 : 000106875X ISBN-13 : 978-0001068759 Poids de l'article : 701 g"
    },
    {
        "ID": 16,
        "Product URL": "https://www.amazon.it/dp/000106875X",
        "Product Title": "Etuden 1 & 2 orgue: Orgel.",
        "Product Image URL": "https://images-na.ssl-images-amazon.com/images/I/31+SH2b7VAL._SX258_BO1,204,203,200_.jpg",
        "Price of the Product": "31,19\u00a0\u20ac",
        "Product Details": "Dettagli prodottoEditore  : SCHOTT (1 gennaio 2000) Lingua  : Francese Spartito musicale  : 12 pagine ISBN-10  : 000106875X ISBN-13  : 978-0001068759 Peso articolo  : 701 g Posizione nella classifica Bestseller di Amazon:n. 12,354 in Educazione e insegnamento musicale n. 22,934 in Strumenti musicali"
    },
    {
        "ID": 17,
        "Product URL": "https://www.amazon.de/dp/000107119X",
        "Product Title": "COMPLETE SONGS WITH PIANO ACCOMPANIMENT BAND 2 CHANT",
        "Product Image URL": "https://images-eu.ssl-images-amazon.com/images/I/41K3KHLZHNL._SX198_BO1,204,203,200_QL40_ML2_.jpg",
        "Price of the Product": "(0%)",
        "Product Details": "Product detailsPublisher  : SCHOTT (1 Jan. 1983) Language  : German ISBN-10  : 000107119X ISBN-13  : 979-0001071192 Best Sellers Rank:4,366,455 in Books (See Top 100 in Books) 3,687 in Vocal Songbooks9,297 in Piano & Keyboards Songbooks39,678 in Piano, Vocal & Guitar Songbooks"
    },
    {
        "ID": 18,
        "Product URL": "https://www.amazon.fr/dp/000107119X",
        "Product Title": "Complete songs with piano accompaniment band 2 chant",
        "Product Image URL": "https://images-eu.ssl-images-amazon.com/images/I/41K3KHLZHNL._SX218_BO1,204,203,200_QL40_ML2_.jpg",
        "Price of the Product": "(0%)",
        "Product Details": "Dtails sur le produitditeur : SCHOTT (1 janvier 1983) Langue : Allemand ISBN-10 : 000107119X ISBN-13 : 979-0001071192 Poids de l'article : 1.5 kg"
    },
    {
        "ID": 19,
        "Product URL": "https://www.amazon.de/dp/000108142X",
        "Product Title": "Orchester-Probespiel Kontrabass: Sammlung wichtiger Passagen aus der Opern- und Konzertliteratur. Kontrabass.",
        "Product Image URL": "https://images-eu.ssl-images-amazon.com/images/I/61OVNlClEDL._SX198_BO1,204,203,200_QL40_ML2_.jpg",
        "Price of the Product": "\u20ac26.00",
        "Product Details": "Product detailsPublisher  : SCHOTT MUSIC GmbH & Co KG, Mainz; 2. Auflage 2008 (29 Jun. 1992) Language  : French Sheet music  : 62 pages ISBN-10  : 000108142X ISBN-13  : 979-0001081429 Dimensions  : 20 x 14 x 4 cm Best Sellers Rank:121,853 in Books (See Top 100 in Books) 355 in String Instruments (Books)630 in Piano, Vocal & Guitar Songbooks38,425 in Foreign Language Books Customer reviews:3.4 out of 5 stars 3 ratings"
    },
    {
        "ID": 20,
        "Product URL": "https://www.amazon.es/dp/000108142X",
        "Product Title": "Spielbuch orchestre",
        "Product Image URL": "https://images-na.ssl-images-amazon.com/images/I/61OVNlClEDL._SX198_BO1,204,203,200_QL40_ML2_.jpg",
        "Price of the Product": "0% (0%)",
        "Product Details": "Detalles del productoEditorial  : SCHOTT (1 enero 2000) Idioma  : Francs ISBN-10  : 000108142X ISBN-13  : 979-0001081429 Peso del producto  : 801 g Dimensiones  : 20 x 14 x 4 cm Clasificacin en los ms vendidos de Amazon:n41,023 en Instrumentos musicales (Ver el Top 100 en Instrumentos musicales) n3,218 en Instrumentos de cuerda (Instrumentos musicales)n5,392 en Bajos y accesorios para bajosn27,909 en Msica (Libros) Opiniones de los clientes:3,4 de 5 estrellas 3 valoraciones"
    },
    {
        "ID": 21,
        "Product URL": "https://www.amazon.fr/dp/000108142X",
        "Product Title": "Spielbuch orchestre",
        "Product Image URL": "https://images-eu.ssl-images-amazon.com/images/I/61OVNlClEDL._SX218_BO1,204,203,200_QL40_ML2_.jpg",
        "Price of the Product": "40,80\u00a0\u20ac",
        "Product Details": "Dtails sur le produitditeur : SCHOTT (1 janvier 2000) Langue : Franais Partition : 62 pages ISBN-10 : 000108142X ISBN-13 : 979-0001081429 Poids de l'article : 801 g Dimensions : 20 x 14 x 4 cm Commentaires client:3,4 sur 5toiles 3 valuations"
    },
    {
        "ID": 22,
        "Product URL": "https://www.amazon.de/dp/000108173X",
        "Product Title": "Wir h\u00f6ren und spielen: Ein Weg zum absoluten Geh\u00f6r. Band 3. Klavier.",
        "Product Image URL": "https://images-eu.ssl-images-amazon.com/images/I/51d3H5bMOmL._SX198_BO1,204,203,200_QL40_ML2_.jpg",
        "Price of the Product": "\u20ac32.00",
        "Product Details": "Product detailsPublisher  : SCHOTT MUSIC GmbH & Co KG, Mainz (17 Jan. 1994) Language  : German Sheet music  : 136 pages ISBN-10  : 000108173X ISBN-13  : 978-0001081734 Best Sellers Rank:853,416 in Books (See Top 100 in Books) 1,080 in Music Techniques1,721 in Elementary Education2,060 in Piano & Keyboards Songbooks Customer reviews:5.0 out of 5 stars 2 ratings"
    },
    {
        "ID": 23,
        "Product URL": "https://www.amazon.fr/dp/000108173X",
        "Product Title": "Wir horen und spielen band 3 piano",
        "Product Image URL": "https://images-eu.ssl-images-amazon.com/images/I/51d3H5bMOmL._SX218_BO1,204,203,200_QL40_ML2_.jpg",
        "Price of the Product": "0% (0%)",
        "Product Details": "Dtails sur le produitditeur : SCHOTT (1 janvier 1994) Langue : Allemand ISBN-10 : 000108173X ISBN-13 : 978-0001081734 Poids de l'article : 1.1 kg Commentaires client:5,0 sur 5toiles 2 valuations"
    },
    {
        "ID": 24,
        "Product URL": "https://www.amazon.fr/dp/000108299X",
        "Product Title": "Arien(2) (grand macabre) 2e akte",
        "Product Image URL": "https://images-eu.ssl-images-amazon.com/images/I/41usGis9EJL._SX218_BO1,204,203,200_QL40_ML2_.jpg",
        "Price of the Product": "35,36\u20ac",
        "Product Details": "Dtails sur le produitditeur : SCHOTT (1 janvier 2000) Langue : Franais ISBN-10 : 000108299X ISBN-13 : 978-0001082991 Poids de l'article : 801 g"
    },
    {
        "ID": 25,
        "Product URL": "https://www.amazon.it/dp/000108299X",
        "Product Title": "Arien(2) (grand macabre) 2e akte",
        "Product Image URL": "https://images-eu.ssl-images-amazon.com/images/I/41usGis9EJL._SX198_BO1,204,203,200_QL40_ML2_.jpg",
        "Price of the Product": "(0%)",
        "Product Details": "Dettagli prodottoEditore  : SCHOTT (1 gennaio 2000) Lingua  : Francese Spartito musicale  : 32 pagine ISBN-10  : 000108299X ISBN-13  : 978-0001082991 Peso articolo  : 801 g"
    },
    {
        "ID": 26,
        "Product URL": "https://www.amazon.fr/dp/000108657X",
        "Product Title": "Fantasie c piano",
        "Product Image URL": "https://images-eu.ssl-images-amazon.com/images/I/41qQkCHj52L._SX218_BO1,204,203,200_QL40_ML2_.jpg",
        "Price of the Product": "9,03\u00a0\u20ac",
        "Product Details": "Dtails sur le produitditeur : SCHOTT (1 janvier 2000) Langue : Franais ISBN-10 : 000108657X ISBN-13 : 978-0001086579 Poids de l'article : 201 g Dimensions : 20 x 14 x 4 cm"
    },
    {
        "ID": 27,
        "Product URL": "https://www.amazon.it/dp/000108657X",
        "Product Title": "Fantasie c piano",
        "Product Image URL": "https://images-eu.ssl-images-amazon.com/images/I/41qQkCHj52L._SX198_BO1,204,203,200_QL40_ML2_.jpg",
        "Price of the Product": "9,03\u00a0\u20ac",
        "Product Details": "Dettagli prodottoEditore  : SCHOTT (1 gennaio 2000) Lingua  : Francese Spartito musicale  : 12 pagine ISBN-10  : 000108657X ISBN-13  : 978-0001086579 Peso articolo  : 201 g Dimensioni  : 20 x 14 x 4 cm"
    },
    {
        "ID": 28,
        "Product URL": "https://www.amazon.de/dp/000108660X",
        "Product Title": "Le Coucou: Rondeau. Klavier. (Edition Schott Einzelausgabe)",
        "Product Image URL": "https://images-eu.ssl-images-amazon.com/images/I/41am5Cllb9L._SX198_BO1,204,203,200_QL40_ML2_.jpg",
        "Price of the Product": "Page 1 of 1",
        "Product Details": "Product detailsPublisher  : SCHOTT MUSIC GmbH & Co KG, Mainz (6 Jan. 1984) Language  : French Sheet music  : 8 pages ISBN-10  : 000108660X ISBN-13  : 978-0001086609 Best Sellers Rank:1,844,276 in Books (See Top 100 in Books) 4,295 in Piano & Keyboards Songbooks18,018 in Piano, Vocal & Guitar Songbooks999,625 in Foreign Language Books Customer reviews:4.6 out of 5 stars 3 ratings"
    },
    {
        "ID": 29,
        "Product URL": "https://www.amazon.fr/dp/000108660X",
        "Product Title": "Coucou piano",
        "Product Image URL": "https://images-eu.ssl-images-amazon.com/images/I/41am5Cllb9L._SX218_BO1,204,203,200_QL40_ML2_.jpg",
        "Price of the Product": "Page 1 sur 1",
        "Product Details": "Dtails sur le produitditeur : SCHOTT (1 janvier 2000) Langue : Franais ISBN-10 : 000108660X ISBN-13 : 978-0001086609 Poids de l'article : 201 g Classement des meilleures ventes d'Amazon :285,127 en Livres (Voir les 100 premiers en Livres) 578 en Partitions musicales pour le clavier et synthtiseur Commentaires client:4,6 sur 5toiles 3 valuations"
    },
    {
        "ID": 30,
        "Product URL": "https://www.amazon.de/dp/000108688X",
        "Product Title": "Adelaide: op. 46. mittlere Singstimme und Klavier. (Edition Schott Einzelausgabe)",
        "Product Image URL": "https://images-eu.ssl-images-amazon.com/images/I/41zo5m7iCzL._SX198_BO1,204,203,200_QL40_ML2_.jpg",
        "Price of the Product": "\u20ac6.50",
        "Product Details": "Product detailsPublisher  : SCHOTT MUSIC GmbH & Co KG, Mainz (30 Jun. 1976) Language  : German, English, French Sheet music  : 12 pages ISBN-10  : 000108688X ISBN-13  : 978-0001086883 Customer reviews:5.0 out of 5 stars 2 ratings"
    },
    {
        "ID": 31,
        "Product URL": "https://www.amazon.fr/dp/000108688X",
        "Product Title": "Adelaide op.46",
        "Product Image URL": "https://images-eu.ssl-images-amazon.com/images/I/41zo5m7iCzL._SX218_BO1,204,203,200_QL40_ML2_.jpg",
        "Price of the Product": "13,20\u00a0\u20ac",
        "Product Details": "Dtails sur le produitditeur : SCHOTT (1 janvier 2000) Langue : Allemand, Anglais, Franais ISBN-10 : 000108688X ISBN-13 : 978-0001086883 Poids de l'article : 201 g Commentaires client:5,0 sur 5toiles 2 valuations"
    },
    {
        "ID": 32,
        "Product URL": "https://www.amazon.de/dp/000108898X",
        "Product Title": "Cavatine: op. 85/3. Violine (Violoncello) und Klavier. (Edition Schott Einzelausgabe)",
        "Product Image URL": "https://images-eu.ssl-images-amazon.com/images/I/410JKNeHjbL._SX198_BO1,204,203,200_QL40_ML2_.jpg",
        "Price of the Product": "(0%)",
        "Product Details": "Product detailsPublisher  : SCHOTT MUSIC GmbH & Co KG, Mainz (15 Mar. 1979) Language  : French Sheet music  : 8 pages ISBN-10  : 000108898X ISBN-13  : 979-0001088985 Best Sellers Rank:2,084,543 in Books (See Top 100 in Books) 3,508 in Strings Songbooks20,521 in Piano, Vocal & Guitar Songbooks1,164,265 in Foreign Language Books"
    },
    {
        "ID": 33,
        "Product URL": "https://www.amazon.fr/dp/000108898X",
        "Product Title": "Cavatine opus 85/3 violon",
        "Product Image URL": "https://images-eu.ssl-images-amazon.com/images/I/410JKNeHjbL._SX218_BO1,204,203,200_QL40_ML2_.jpg",
        "Price of the Product": "(0%)",
        "Product Details": "Dtails sur le produitditeur : SCHOTT (1 janvier 2000) Langue : Franais ISBN-10 : 000108898X ISBN-13 : 979-0001088985 Poids de l'article : 201 g"
    },
    {
        "ID": 34,
        "Product URL": "https://www.amazon.de/dp/000108917X",
        "Product Title": "Gnomenreigen: Konzert-Et\u00fcde. Klavier. (Edition Schott Einzelausgabe)",
        "Product Image URL": "https://images-eu.ssl-images-amazon.com/images/I/41A1-6T49fL._SX198_BO1,204,203,200_QL40_ML2_.jpg",
        "Price of the Product": "\u20ac5.50",
        "Product Details": "Product detailsPublisher  : SCHOTT MUSIC GmbH & Co KG, Mainz (15 Mar. 1978) Language  : French Sheet music  : 12 pages ISBN-10  : 000108917X ISBN-13  : 978-0001089174 Best Sellers Rank:1,684,192 in Books (See Top 100 in Books) 3,923 in Piano & Keyboards Songbooks16,303 in Piano, Vocal & Guitar Songbooks894,962 in Foreign Language Books Customer reviews:5.0 out of 5 stars 1 rating"
    },
    {
        "ID": 35,
        "Product URL": "https://www.amazon.fr/dp/000108917X",
        "Product Title": "Gnomenreigen piano",
        "Product Image URL": "https://images-eu.ssl-images-amazon.com/images/I/41A1-6T49fL._SX218_BO1,204,203,200_QL40_ML2_.jpg",
        "Price of the Product": "9,03\u00a0\u20ac",
        "Product Details": "Dtails sur le produitditeur : SCHOTT (1 janvier 2000) Langue : Franais ISBN-10 : 000108917X ISBN-13 : 978-0001089174 Poids de l'article : 201 g Commentaires client:5,0 sur 5toiles 1 valuation"
    },
    {
        "ID": 36,
        "Product URL": "https://www.amazon.de/dp/000109212X",
        "Product Title": "Moto perpetuo: op. 11. Violine und Klavier. (Edition Schott Einzelausgabe)",
        "Product Image URL": "https://images-eu.ssl-images-amazon.com/images/I/41L-o9AvBSL._SX198_BO1,204,203,200_QL40_ML2_.jpg",
        "Price of the Product": "\u20ac6.50",
        "Product Details": "Product detailsPublisher  : SCHOTT MUSIC GmbH & Co KG, Mainz (26 Aug. 1985) Language  : French Sheet music  : 16 pages ISBN-10  : 000109212X ISBN-13  : 978-0001092129 Best Sellers Rank:4,329,520 in Books (See Top 100 in Books) 1,514 in Violins (Books)6,267 in Strings Songbooks39,434 in Piano, Vocal & Guitar Songbooks Customer reviews:4.5 out of 5 stars 2 ratings"
    },
    {
        "ID": 37,
        "Product URL": "https://www.amazon.fr/dp/000109212X",
        "Product Title": "Moto perpetuo violon",
        "Product Image URL": "https://images-eu.ssl-images-amazon.com/images/I/41L-o9AvBSL._SX218_BO1,204,203,200_QL40_ML2_.jpg",
        "Price of the Product": "10,60\u00a0\u20ac",
        "Product Details": "Dtails sur le produitditeur : SCHOTT (1 janvier 2000) Langue : Franais ISBN-10 : 000109212X ISBN-13 : 978-0001092129 Poids de l'article : 201 g Commentaires client:4,5 sur 5toiles 2 valuations"
    },
    {
        "ID": 38,
        "Product URL": "https://www.amazon.de/dp/000109257X",
        "Product Title": "Happy Birthday: Humoristische Variationen \u00fcber ein Geburtstagslied. Klavier 4-h\u00e4ndig. (Edition Schott Einzelausgabe)",
        "Product Image URL": "https://images-eu.ssl-images-amazon.com/images/I/41wLZGTLuGL._SX198_BO1,204,203,200_QL40_ML2_.jpg",
        "Price of the Product": "\u20ac6.50",
        "Product Details": "Product detailsPublisher  : SCHOTT MUSIC GmbH & Co KG, Mainz (13 Jan. 1988) Language  : French Sheet music  : 16 pages ISBN-10  : 000109257X ISBN-13  : 978-0001092570 Best Sellers Rank:1,044,393 in Books (See Top 100 in Books) 2,473 in Piano & Keyboards Songbooks9,482 in Piano, Vocal & Guitar Songbooks505,719 in Foreign Language Books Customer reviews:5.0 out of 5 stars 1 rating"
    },
    {
        "ID": 39,
        "Product URL": "https://www.amazon.fr/dp/000109257X",
        "Product Title": "Happy birthday piano",
        "Product Image URL": "https://images-eu.ssl-images-amazon.com/images/I/41wLZGTLuGL._SX218_BO1,204,203,200_QL40_ML2_.jpg",
        "Price of the Product": "0% (0%)",
        "Product Details": "Dtails sur le produitditeur : SCHOTT (1 janvier 2000) Langue : Franais ISBN-10 : 000109257X ISBN-13 : 978-0001092570 Poids de l'article : 201 g Commentaires client:5,0 sur 5toiles 1 valuation"
    },
    {
        "ID": 40,
        "Product URL": "https://www.amazon.de/dp/000109453X",
        "Product Title": "6 Duos: op. 1. 2 Fl\u00f6ten. Spielpartitur. (Edition Schott)",
        "Product Image URL": "https://images-eu.ssl-images-amazon.com/images/I/41yNWRfXqDL._SX198_BO1,204,203,200_QL40_ML2_.jpg",
        "Price of the Product": "\u20ac24.50",
        "Product Details": "Product detailsPublisher  : SCHOTT MUSIC GmbH & Co KG, Mainz (8 Mar. 1994) Language  : French Sheet music  : 56 pages ISBN-10  : 000109453X ISBN-13  : 978-0001094536 Best Sellers Rank:3,481,084 in Books (See Top 100 in Books) 1,032 in Flute Songbooks33,757 in Piano, Vocal & Guitar Songbooks2,225,317 in Foreign Language Books Customer reviews:5.0 out of 5 stars 1 rating"
    },
    {
        "ID": 41,
        "Product URL": "https://www.amazon.fr/dp/000109453X",
        "Product Title": "Duos(6) opus 1 flute traversiere",
        "Product Image URL": "https://images-eu.ssl-images-amazon.com/images/I/41yNWRfXqDL._SX218_BO1,204,203,200_QL40_ML2_.jpg",
        "Price of the Product": "33,14\u00a0\u20ac",
        "Product Details": "Dtails sur le produitditeur : SCHOTT (1 janvier 2000) Langue : Franais ISBN-10 : 000109453X ISBN-13 : 978-0001094536 Poids de l'article : 701 g Commentaires client:5,0 sur 5toiles 1 valuation"
    },
    {
        "ID": 42,
        "Product URL": "https://www.amazon.de/dp/000109825X",
        "Product Title": "Cs\u00e1rd\u00e1s-Kompositionen: Klarinette und Klavier. (Edition Schott)",
        "Product Image URL": "https://images-eu.ssl-images-amazon.com/images/I/41vzotqLOgL._SX198_BO1,204,203,200_QL40_ML2_.jpg",
        "Price of the Product": "\u20ac16.00",
        "Product Details": "Product detailsPublisher  : SCHOTT MUSIC GmbH & Co KG, Mainz (3 Oct. 1988) Language  : French Sheet music  : 31 pages ISBN-10  : 000109825X ISBN-13  : 979-0001098250 Best Sellers Rank:1,123,114 in Books (See Top 100 in Books) 142 in Clarinet Songbooks10,299 in Piano, Vocal & Guitar Songbooks551,654 in Foreign Language Books Customer reviews:3.0 out of 5 stars 1 rating"
    },
    {
        "ID": 43,
        "Product URL": "https://www.amazon.fr/dp/000109825X",
        "Product Title": "Csardas-kompositionen clarinette",
        "Product Image URL": "https://images-eu.ssl-images-amazon.com/images/I/41vzotqLOgL._SX218_BO1,204,203,200_QL40_ML2_.jpg",
        "Price of the Product": "26,26\u00a0\u20ac",
        "Product Details": "Dtails sur le produitditeur : SCHOTT (1 janvier 2000) Langue : Franais ISBN-10 : 000109825X ISBN-13 : 979-0001098250 Poids de l'article : 120 g Classement des meilleures ventes d'Amazon :1,006,039 en Livres (Voir les 100 premiers en Livres) 257 en Partitions musicales pour la clarinette291 en Clarinettes (Livres) Commentaires client:3,0 sur 5toiles 1 valuation"
    },
    {
        "ID": 44,
        "Product URL": "https://www.amazon.de/dp/000110733X",
        "Product Title": "S\u00e9r\u00e9nade espagnole: Violine und Klavier. (Edition Schott, Nr. 26)",
        "Product Image URL": "https://images-eu.ssl-images-amazon.com/images/I/419YG5nPHEL._SX198_BO1,204,203,200_QL40_ML2_.jpg",
        "Price of the Product": "\u20ac9.00",
        "Product Details": "Product detailsPublisher  : SCHOTT MUSIC GmbH & Co KG, Mainz (26 Aug. 1985) Language  : French Sheet music  : 8 pages ISBN-10  : 000110733X ISBN-13  : 978-0001107335 Best Sellers Rank:4,465,911 in Books (See Top 100 in Books) 1,546 in Violins (Books)40,365 in Piano, Vocal & Guitar Songbooks3,040,483 in Foreign Language Books"
    },
    {
        "ID": 45,
        "Product URL": "https://www.amazon.fr/dp/000110733X",
        "Product Title": "Serenata spagnola (kreisler) violon",
        "Product Image URL": "https://images-eu.ssl-images-amazon.com/images/I/419YG5nPHEL._SX218_BO1,204,203,200_QL40_ML2_.jpg",
        "Price of the Product": "14,77\u00a0\u20ac",
        "Product Details": "Dtails sur le produitditeur : SCHOTT (1 janvier 2000) Langue : Franais Partition : 7 pages ISBN-10 : 000110733X ISBN-13 : 978-0001107335 Poids de l'article : 401 g Classement des meilleures ventes d'Amazon :1,971,035 en Livres (Voir les 100 premiers en Livres) 1,423 en Violons (Livres)6,949 en Partitions musicales pour les instruments  cordes"
    },
    {
        "ID": 46,
        "Product URL": "https://www.amazon.de/dp/000111252X",
        "Product Title": "Eingedunkelt: Neun Gedichte nach Paul Celan. Alt-Solo. Alt.",
        "Product Image URL": "https://images-eu.ssl-images-amazon.com/images/I/41suSIrxOHL._SX198_BO1,204,203,200_QL40_ML2_.jpg",
        "Price of the Product": "(0%)",
        "Product Details": "Product detailsPublisher  : SCHOTT MUSIC GmbH & Co KG, Mainz (22 Dec. 1995) Language  : German Sheet music  : 16 pages ISBN-10  : 000111252X ISBN-13  : 979-0001112529 Best Sellers Rank:3,033,087 in Books (See Top 100 in Books) 29,754 in Piano, Vocal & Guitar Songbooks"
    },
    {
        "ID": 47,
        "Product URL": "https://www.amazon.fr/dp/000111252X",
        "Product Title": "Eingedunkelt",
        "Product Image URL": "https://images-eu.ssl-images-amazon.com/images/I/41suSIrxOHL._SX218_BO1,204,203,200_QL40_ML2_.jpg",
        "Price of the Product": "(0%)",
        "Product Details": "Dtails sur le produitditeur : SCHOTT (1 janvier 1995) Langue : Allemand ISBN-10 : 000111252X ISBN-13 : 979-0001112529 Poids de l'article : 601 g"
    },
    {
        "ID": 48,
        "Product URL": "https://www.amazon.de/dp/000115687X",
        "Product Title": "Viola Spaces: Contemporary Viola Studies. Band 1. Viola. (Essential Exercises, Band 1)",
        "Product Image URL": "https://images-eu.ssl-images-amazon.com/images/I/41Y-4h2wgsL._SX198_BO1,204,203,200_QL40_ML2_.jpg",
        "Price of the Product": "(0%)",
        "Product Details": "Product detailsPublisher  : SCHOTT MUSIC GmbH & Co KG, Mainz (9 Mar. 2009) Language  : German, English Sheet music  : 48 pages ISBN-10  : 000115687X ISBN-13  : 978-0001156876 Best Sellers Rank:3,876,519 in Books (See Top 100 in Books) 97 in Viola Songbooks13,432 in String Instruments (Books)18,219 in Music Instruction & Study"
    },
    {
        "ID": 49,
        "Product URL": "https://www.amazon.fr/dp/000115687X",
        "Product Title": "Viola spaces vol. 1 alto",
        "Product Image URL": "https://images-eu.ssl-images-amazon.com/images/I/41Y-4h2wgsL._SX218_BO1,204,203,200_QL40_ML2_.jpg",
        "Price of the Product": "43,02\u00a0\u20ac",
        "Product Details": "Dtails sur le produitditeur : SCHOTT (1 janvier 2009) Langue : Allemand, Anglais ISBN-10 : 000115687X ISBN-13 : 978-0001156876 Poids de l'article : 801 g"
    },
    {
        "ID": 50,
        "Product URL": "https://www.amazon.de/dp/000416041X",
        "Product Title": "Klaviertrio G-Dur Hob XV:15 (EB 1131)",
        "Product Image URL": "https://images-eu.ssl-images-amazon.com/images/I/41zx75efEBL._SX198_BO1,204,203,200_QL40_ML2_.jpg",
        "Price of the Product": "\u20ac13.90",
        "Product Details": "Product detailsPublisher  : Breitkopf & Hrtel (31 May 1966) Language  : German Paperback  : 40 pages ISBN-10  : 000416041X ISBN-13  : 979-0004160411 Best Sellers Rank:3,595,647 in Books (See Top 100 in Books) 67,622 in Scores, Songbooks & Lyrics"
    },
    {
        "ID": 51,
        "Product URL": "https://www.amazon.fr/dp/000416041X",
        "Product Title": "Klavier-trio g-dur hob xv: 15",
        "Product Image URL": "https://images-eu.ssl-images-amazon.com/images/I/41zx75efEBL._SX218_BO1,204,203,200_QL40_ML2_.jpg",
        "Price of the Product": "(0%)",
        "Product Details": "Dtails sur le produitditeur : BREITKOPF (1 janvier 2000) Langue : Allemand Broch : 40 pages ISBN-10 : 000416041X ISBN-13 : 979-0004160411 Poids de l'article : 401 g"
    },
    {
        "ID": 52,
        "Product URL": "https://www.amazon.de/dp/000416105X",
        "Product Title": "VIOLINKONZERT 2 D-DUR KV 211",
        "Product Image URL": "https://images-eu.ssl-images-amazon.com/images/I/51Qp-R83kUL._SX198_BO1,204,203,200_QL40_ML2_.jpg",
        "Price of the Product": "(0%)",
        "Product Details": "Product detailsPublisher  : BREITKOPF (1 Jan. 2000) Language  : French ISBN-10  : 000416105X ISBN-13  : 978-0004161051"
    },
    {
        "ID": 53,
        "Product URL": "https://www.amazon.fr/dp/000416105X",
        "Product Title": "Violinkonzert 2 d-dur kv 211",
        "Product Image URL": "https://images-eu.ssl-images-amazon.com/images/I/51Qp-R83kUL._SX218_BO1,204,203,200_QL40_ML2_.jpg",
        "Price of the Product": "25,02\u00a0\u20ac",
        "Product Details": "Dtails sur le produitditeur : BREITKOPF (1 janvier 2000) Langue : Franais ISBN-10 : 000416105X ISBN-13 : 978-0004161051 Poids de l'article : 340 g"
    },
    {
        "ID": 54,
        "Product URL": "https://www.amazon.fr/dp/000416198X",
        "Product Title": "2 divertimenti kv 252, kv 240",
        "Product Image URL": "https://images-eu.ssl-images-amazon.com/images/I/41H73ri0GDL._SY291_BO1,204,203,200_QL40_ML2_.jpg",
        "Price of the Product": "22,37\u00a0\u20ac",
        "Product Details": "Dtails sur le produitditeur : BREITKOPF (1 janvier 2000) Langue : Allemand Broch : 36 pages ISBN-10 : 000416198X ISBN-13 : 978-0004161983 Poids de l'article : 1 kg"
    },
    {
        "ID": 55,
        "Product URL": "https://www.amazon.it/dp/000416198X",
        "Product Title": "2 leichte Divertimenti f\u00fcr Violine (Oboe), Cello (Fagott) und Klavier - Es-dur KV 252 (240a) und B-dur KV 240 - Bearbeitung (EB 3810)",
        "Product Image URL": "https://images-eu.ssl-images-amazon.com/images/I/41H73ri0GDL._SY264_BO1,204,203,200_QL40_ML2_.jpg",
        "Price of the Product": "22,37\u00a0\u20ac",
        "Product Details": "Dettagli prodottoEditore  : Breitkopf & Hrtel (1 gennaio 2000) Lingua  : Tedesco Copertina flessibile  : 36 pagine ISBN-10  : 000416198X ISBN-13  : 978-0004161983 Peso articolo  : 1 kg"
    },
    {
        "ID": 56,
        "Product URL": "https://www.amazon.de/dp/000416413X",
        "Product Title": "Il Re pastore KV 208 - L'amer\u00f2, sar\u00f2 costante - Arie der Aminta - Ausgabe f\u00fcr Sorpan, Violine und Klavier (EB 5473)",
        "Product Image URL": "https://images-eu.ssl-images-amazon.com/images/I/41YwjHe4wkL._SX198_BO1,204,203,200_QL40_ML2_.jpg",
        "Price of the Product": "\u20ac7.90",
        "Product Details": "Product detailsPublisher  : Breitkopf & Hrtel (5 Nov. 1963) Language  : German Sheet music  : 10 pages ISBN-10  : 000416413X ISBN-13  : 978-0004164137 Best Sellers Rank:2,128,566 in Books (See Top 100 in Books) 3,543 in Scores, Songbooks & Lyrics for Opera & Classical Music"
    },
    {
        "ID": 57,
        "Product URL": "https://www.amazon.fr/dp/000416413X",
        "Product Title": "L'amero/dein bin ich kv 208",
        "Product Image URL": "https://images-eu.ssl-images-amazon.com/images/I/41YwjHe4wkL._SX218_BO1,204,203,200_QL40_ML2_.jpg",
        "Price of the Product": "10,55\u00a0\u20ac",
        "Product Details": "Dtails sur le produitditeur : BREITKOPF (1 janvier 2000) Langue : Allemand Partition : 10 pages ISBN-10 : 000416413X ISBN-13 : 978-0004164137 Poids de l'article : 201 g"
    },
    {
        "ID": 58,
        "Product URL": "https://www.amazon.de/dp/000416444X",
        "Product Title": "Sonate op. 41 - Ausgabe f\u00fcr Fagott und Klavier (EB 5567)",
        "Product Image URL": "https://images-eu.ssl-images-amazon.com/images/I/41aptNQZHrL._SX198_BO1,204,203,200_QL40_ML2_.jpg",
        "Price of the Product": "\u20ac35.90",
        "Product Details": "Product detailsPublisher  : Breitkopf & Hrtel (21 Mar. 1961) Language  : German Paperback  : 36 pages ISBN-10  : 000416444X ISBN-13  : 978-0004164441"
    },
    {
        "ID": 59,
        "Product URL": "https://www.amazon.fr/dp/000416444X",
        "Product Title": "Sonate op. 41 basson",
        "Product Image URL": "https://images-eu.ssl-images-amazon.com/images/I/41aptNQZHrL._SX218_BO1,204,203,200_QL40_ML2_.jpg",
        "Price of the Product": "47,69\u00a0\u20ac",
        "Product Details": "Dtails sur le produitditeur : BREITKOPF (1 janvier 2000) Langue : Allemand Broch : 36 pages ISBN-10 : 000416444X ISBN-13 : 978-0004164441 Poids de l'article : 140 g"
    },
    {
        "ID": 60,
        "Product URL": "https://www.amazon.de/dp/000416508X",
        "Product Title": "Quintett B-dur op. 34 - Breitkopf Urtext - Stimmensatz (EB 5830)",
        "Product Image URL": "https://images-eu.ssl-images-amazon.com/images/I/41QN-6dasEL._SX198_BO1,204,203,200_QL40_ML2_.jpg",
        "Price of the Product": "\u20ac25.90",
        "Product Details": "Product detailsPublisher  : Breitkopf & Hrtel (29 April 1966) Language  : German Paperback  : 68 pages ISBN-10  : 000416508X ISBN-13  : 978-0004165080 Dimensions  : 30.51 x 23.01 x 0.48 cm"
    },
    {
        "ID": 61,
        "Product URL": "https://www.amazon.fr/dp/000416508X",
        "Product Title": "Quintett b-dur op. 34 clarinette",
        "Product Image URL": "https://images-eu.ssl-images-amazon.com/images/I/41QN-6dasEL._SX218_BO1,204,203,200_QL40_ML2_.jpg",
        "Price of the Product": "36,44\u00a0\u20ac",
        "Product Details": "Dtails sur le produitditeur : BREITKOPF (1 janvier 2000) Langue : Allemand Broch : 68 pages ISBN-10 : 000416508X ISBN-13 : 978-0004165080 Poids de l'article : 500 g Dimensions : 30.51 x 23.01 x 0.48 cm"
    },
    {
        "ID": 62,
        "Product URL": "https://www.amazon.de/dp/000416511X",
        "Product Title": "Sonate B-dur f\u00fcr Fl\u00f6te und Klavier (EB 5879)",
        "Product Image URL": "https://images-eu.ssl-images-amazon.com/images/I/515ZbxjDfLL._SY264_BO1,204,203,200_QL40_ML2_.jpg",
        "Price of the Product": "\u20ac15.90",
        "Product Details": "Product detailsPublisher  : Breitkopf & Hrtel (14 Feb. 1969) Language  : German Sheet music  : 36 pages ISBN-10  : 000416511X ISBN-13  : 979-0004165119 Best Sellers Rank:2,430,531 in Books (See Top 100 in Books) 24,111 in Piano, Vocal & Guitar Songbooks"
    },
    {
        "ID": 63,
        "Product URL": "https://www.amazon.fr/dp/000416511X",
        "Product Title": "Sonate bes flute traversiere",
        "Product Image URL": "https://images-eu.ssl-images-amazon.com/images/I/515ZbxjDfLL._SY291_BO1,204,203,200_QL40_ML2_.jpg",
        "Price of the Product": "20,96\u00a0\u20ac",
        "Product Details": "Dtails sur le produitditeur : BREITKOPF (1 janvier 2000) Langue : Allemand Partition : 36 pages ISBN-10 : 000416511X ISBN-13 : 979-0004165119 Poids de l'article : 501 g Classement des meilleures ventes d'Amazon :1,706,590 en Livres (Voir les 100 premiers en Livres) 874 en Fltes3,128 en Partitions musicales pour les bois"
    },
    {
        "ID": 64,
        "Product URL": "https://www.amazon.fr/dp/000416816X",
        "Product Title": "Chaconne d-moll aus bwv 1004",
        "Product Image URL": "https://images-eu.ssl-images-amazon.com/images/I/41lrIDbi75L._SY291_BO1,204,203,200_QL40_ML2_.jpg",
        "Price of the Product": "13,93\u00a0\u20ac",
        "Product Details": "Dtails sur le produitditeur : BREITKOPF (1 janvier 2000) Langue : Allemand Partition : 16 pages ISBN-10 : 000416816X ISBN-13 : 978-0004168166 Poids de l'article : 401 g"
    },
    {
        "ID": 65,
        "Product URL": "https://www.amazon.it/dp/000416816X",
        "Product Title": "Chaconne aus der Partita II d-moll BWV 1004 Bearbeitung f\u00fcr Cembalo (EB 6594)",
        "Product Image URL": "https://images-eu.ssl-images-amazon.com/images/I/41lrIDbi75L._SY264_BO1,204,203,200_QL40_ML2_.jpg",
        "Price of the Product": "13,93\u00a0\u20ac",
        "Product Details": "Dettagli prodottoEditore  : Breitkopf & Hrtel (1 gennaio 2000) Lingua  : Tedesco Spartito musicale  : 16 pagine ISBN-10  : 000416816X ISBN-13  : 978-0004168166 Peso articolo  : 401 g"
    },
    {
        "ID": 66,
        "Product URL": "https://www.amazon.de/dp/000416976X",
        "Product Title": "LITANIAE DE VENERABILI KV 243",
        "Product Image URL": "https://images-na.ssl-images-amazon.com/images/I/414wyAfP+WL._SY344_BO1,204,203,200_.jpg",
        "Price of the Product": "\u20ac12.55",
        "Product Details": "Product detailsPublisher  : BREITKOPF (1 Jan. 2000) Language  : French ISBN-10  : 000416976X ISBN-13  : 979-0004169766"
    },
    {
        "ID": 67,
        "Product URL": "https://www.amazon.fr/dp/000416976X",
        "Product Title": "Litaniae de venerabili kv 243",
        "Product Image URL": "https://images-na.ssl-images-amazon.com/images/I/414wyAfP+WL._SY344_BO1,204,203,200_.jpg",
        "Price of the Product": "12,26\u00a0\u20ac",
        "Product Details": "Dtails sur le produitditeur : BREITKOPF (1 janvier 2000) Langue : Franais ISBN-10 : 000416976X ISBN-13 : 979-0004169766 Poids de l'article : 501 g"
    },
    {
        "ID": 68,
        "Product URL": "https://www.amazon.de/dp/000417156X",
        "Product Title": "Kantate 2 Ach Gott, Vom",
        "Product Image URL": "https://images-eu.ssl-images-amazon.com/images/I/41Suo9QtJ2L._SY264_BO1,204,203,200_QL40_ML2_.jpg",
        "Price of the Product": "\u20ac8.16",
        "Product Details": "Product detailsPublisher  : BREITKOPF; Klavierauszug deutsch/englisch edition (1 Jan. 2000) Language  : French Sheet music  : 27 pages ISBN-10  : 000417156X ISBN-13  : 979-0004171561 Dimensions  : 27 x 19 x 0.41 cm"
    },
    {
        "ID": 69,
        "Product URL": "https://www.amazon.fr/dp/000417156X",
        "Product Title": "Kantate 2 ach gott, vom",
        "Product Image URL": "https://images-eu.ssl-images-amazon.com/images/I/41Suo9QtJ2L._SY291_BO1,204,203,200_QL40_ML2_.jpg",
        "Price of the Product": "5,82\u00a0\u20ac",
        "Product Details": "Dtails sur le produitditeur : BREITKOPF (1 janvier 2000) Langue : Franais ISBN-10 : 000417156X ISBN-13 : 979-0004171561 Poids de l'article : 201 g Dimensions : 27 x 19 x 0.41 cm"
    },
    {
        "ID": 70,
        "Product URL": "https://www.amazon.de/dp/000417173X",
        "Product Title": "Kantate 19 Es Erhub Sich Ein",
        "Product Image URL": "https://images-eu.ssl-images-amazon.com/images/I/41xQZu3zHbL._SY264_BO1,204,203,200_QL40_ML2_.jpg",
        "Price of the Product": "\u20ac11.26",
        "Product Details": "Product detailsPublisher  : BREITKOPF; Klavierauszug Leipzig 1983 edition (1 Jan. 2000) Language  : French Sheet music  : 28 pages ISBN-10  : 000417173X ISBN-13  : 978-0004171739"
    },
    {
        "ID": 71,
        "Product URL": "https://www.amazon.fr/dp/000417173X",
        "Product Title": "Kantate 19 es erhub sich ein",
        "Product Image URL": "https://images-eu.ssl-images-amazon.com/images/I/41xQZu3zHbL._SY291_BO1,204,203,200_QL40_ML2_.jpg",
        "Price of the Product": "7,42\u00a0\u20ac",
        "Product Details": "Dtails sur le produitditeur : BREITKOPF (1 janvier 2000) Langue : Franais ISBN-10 : 000417173X ISBN-13 : 978-0004171739 Poids de l'article : 301 g"
    },
    {
        "ID": 72,
        "Product URL": "https://www.amazon.de/dp/000417206X",
        "Product Title": "Kantate 52 Falsche Welt, Dir",
        "Product Image URL": "https://images-eu.ssl-images-amazon.com/images/I/41mTrzyK76L._SY264_BO1,204,203,200_QL40_ML2_.jpg",
        "Price of the Product": "\u20ac7.39",
        "Product Details": "Product detailsPublisher  : BREITKOPF; Klavierauszug Leipzig 1984 edition (1 Jan. 2000) Language  : French Sheet music  : 20 pages ISBN-10  : 000417206X ISBN-13  : 978-0004172064 Best Sellers Rank:4,484,153 in Books (See Top 100 in Books) 1,719 in Choral Songbooks3,056,055 in Foreign Language Books Customer reviews:5.0 out of 5 stars 1 rating"
    },
    {
        "ID": 73,
        "Product URL": "https://www.amazon.fr/dp/000417206X",
        "Product Title": "Kantate 52 falsche welt, dir",
        "Product Image URL": "https://images-eu.ssl-images-amazon.com/images/I/41mTrzyK76L._SY291_BO1,204,203,200_QL40_ML2_.jpg",
        "Price of the Product": "6,21\u00a0\u20ac",
        "Product Details": "Dtails sur le produitditeur : BREITKOPF (1 janvier 2000) Langue : Franais ISBN-10 : 000417206X ISBN-13 : 978-0004172064 Poids de l'article : 201 g"
    },
    {
        "ID": 74,
        "Product URL": "https://www.amazon.de/dp/000417237X",
        "Product Title": "KANTATE 083 ERFREUTE ZEIT IM",
        "Product Image URL": "https://images-eu.ssl-images-amazon.com/images/I/41d0FaBiSTL._SY264_BO1,204,203,200_QL40_ML2_.jpg",
        "Price of the Product": "\u20ac6.50",
        "Product Details": "Product detailsPublisher  : BREITKOPF; Klavierauszug Leipzig 1988 edition (1 Jan. 2000) Language  : French Sheet music  : 18 pages ISBN-10  : 000417237X ISBN-13  : 979-0004172377"
    },
    {
        "ID": 75,
        "Product URL": "https://www.amazon.fr/dp/000417237X",
        "Product Title": "Kantate 083 erfreute zeit im",
        "Product Image URL": "https://images-eu.ssl-images-amazon.com/images/I/41d0FaBiSTL._SY291_BO1,204,203,200_QL40_ML2_.jpg",
        "Price of the Product": "(0%)",
        "Product Details": "Dtails sur le produitditeur : BREITKOPF (1 janvier 2000) Langue : Franais ISBN-10 : 000417237X ISBN-13 : 979-0004172377 Poids de l'article : 201 g"
    },
    {
        "ID": 76,
        "Product URL": "https://www.amazon.de/dp/000417240X",
        "Product Title": "Kantate 86 Wahrlich, Wahrlich",
        "Product Image URL": "https://images-eu.ssl-images-amazon.com/images/I/41aWBN0BW1L._SY264_BO1,204,203,200_QL40_ML2_.jpg",
        "Price of the Product": "\u20ac6.50",
        "Product Details": "Product detailsPublisher  : BREITKOPF; Klavierauszug Leipzig 1983 edition (1 Jan. 2000) Language  : French Paperback  : 20 pages ISBN-10  : 000417240X ISBN-13  : 979-0004172407"
    },
    {
        "ID": 77,
        "Product URL": "https://www.amazon.fr/dp/000417240X",
        "Product Title": "Kantate 86 wahrlich, wahrlich",
        "Product Image URL": "https://images-eu.ssl-images-amazon.com/images/I/41aWBN0BW1L._SY291_BO1,204,203,200_QL40_ML2_.jpg",
        "Price of the Product": "(0%)",
        "Product Details": "Dtails sur le produitditeur : BREITKOPF (1 janvier 2000) Langue : Franais ISBN-10 : 000417240X ISBN-13 : 979-0004172407 Poids de l'article : 201 g"
    },
    {
        "ID": 78,
        "Product URL": "https://www.amazon.de/dp/000417268X",
        "Product Title": "Kantate 114 Ach Lieben",
        "Product Image URL": "https://images-eu.ssl-images-amazon.com/images/I/41mIiAzCWsL._SY264_BO1,204,203,200_QL40_ML2_.jpg",
        "Price of the Product": "\u20ac8.50",
        "Product Details": "Product detailsPublisher  : BREITKOPF; Klavierauszug Leipzig 1985 edition (1 Jan. 2000) Language  : French Paperback  : 28 pages ISBN-10  : 000417268X ISBN-13  : 979-0004172681"
    },
    {
        "ID": 79,
        "Product URL": "https://www.amazon.fr/dp/000417268X",
        "Product Title": "Kantate 114 ach lieben",
        "Product Image URL": "https://images-eu.ssl-images-amazon.com/images/I/41mIiAzCWsL._SY291_BO1,204,203,200_QL40_ML2_.jpg",
        "Price of the Product": "(0%)",
        "Product Details": "Dtails sur le produitditeur : BREITKOPF (1 janvier 2000) Langue : Franais ISBN-10 : 000417268X ISBN-13 : 979-0004172681 Poids de l'article : 201 g"
    },
    {
        "ID": 80,
        "Product URL": "https://www.amazon.de/dp/000417271X",
        "Product Title": "Kantate 117 Sie Lob Und Ehr",
        "Product Image URL": "https://images-eu.ssl-images-amazon.com/images/I/41hlFmvlMsL._SY264_BO1,204,203,200_QL40_ML2_.jpg",
        "Price of the Product": "\u20ac9.15",
        "Product Details": "Product detailsPublisher  : BREITKOPF; Klavierauszug deutsch/englisch edition (1 Jan. 2000) Language  : French Pamphlet  : 28 pages ISBN-10  : 000417271X ISBN-13  : 978-0004172712 Best Sellers Rank:2,968,381 in Books (See Top 100 in Books) 1,210 in Choral Songbooks1,818,196 in Foreign Language Books"
    },
    {
        "ID": 81,
        "Product URL": "https://www.amazon.fr/dp/000417271X",
        "Product Title": "Kantate 117 sie lob und ehr",
        "Product Image URL": "https://images-eu.ssl-images-amazon.com/images/I/41hlFmvlMsL._SY291_BO1,204,203,200_QL40_ML2_.jpg",
        "Price of the Product": "7,89\u00a0\u20ac",
        "Product Details": "Dtails sur le produitditeur : BREITKOPF (1 janvier 2000) Langue : Franais ISBN-10 : 000417271X ISBN-13 : 978-0004172712 Poids de l'article : 201 g"
    },
    {
        "ID": 82,
        "Product URL": "https://www.amazon.de/dp/000417318X",
        "Product Title": "Bach, Kantate 164, Ihr, die ihr euch von Christo nennet",
        "Product Image URL": "https://images-na.ssl-images-amazon.com/images/I/41+g+QbpBFL._SX258_BO1,204,203,200_.jpg",
        "Price of the Product": "\u20ac7.39",
        "Product Details": "Product detailsPublisher  : BREITKOPF; Klavierauszug Leipzig 1986 edition (1 Jan. 2000) Language  : French Paperback  : 20 pages ISBN-10  : 000417318X ISBN-13  : 979-0004173183"
    },
    {
        "ID": 83,
        "Product URL": "https://www.amazon.fr/dp/000417318X",
        "Product Title": "Kantate 164 ihr die ihr euch",
        "Product Image URL": "https://images-na.ssl-images-amazon.com/images/I/41+g+QbpBFL._SX258_BO1,204,203,200_.jpg",
        "Price of the Product": "(0%)",
        "Product Details": "Dtails sur le produitditeur : BREITKOPF (1 janvier 2000) Langue : Franais ISBN-10 : 000417318X ISBN-13 : 979-0004173183 Poids de l'article : 201 g"
    },
    {
        "ID": 84,
        "Product URL": "https://www.amazon.de/dp/000417335X",
        "Product Title": "Kantate 181 Leichtgesinnte",
        "Product Image URL": "https://images-eu.ssl-images-amazon.com/images/I/31D4bTOuJaL._SY264_BO1,204,203,200_QL40_ML2_.jpg",
        "Price of the Product": "\u20ac6.50",
        "Product Details": "Product detailsPublisher  : BREITKOPF (1 Jan. 2000) Language  : French ISBN-10  : 000417335X ISBN-13  : 978-0004173351"
    },
    {
        "ID": 85,
        "Product URL": "https://www.amazon.fr/dp/000417335X",
        "Product Title": "Kantate 181 leichtgesinnte",
        "Product Image URL": "https://images-eu.ssl-images-amazon.com/images/I/31D4bTOuJaL._SY291_BO1,204,203,200_QL40_ML2_.jpg",
        "Price of the Product": "(0%)",
        "Product Details": "Dtails sur le produitditeur : BREITKOPF (1 janvier 2000) Langue : Franais ISBN-10 : 000417335X ISBN-13 : 978-0004173351 Poids de l'article : 201 g"
    },
    {
        "ID": 86,
        "Product URL": "https://www.amazon.de/dp/000417805X",
        "Product Title": "Fantasie \u00fcber den Choral 'Ein feste Burg ist unser Gott' op. 27 f\u00fcr Orgel - Breitkopf Urtext (EB 8512)",
        "Product Image URL": "https://images-eu.ssl-images-amazon.com/images/I/418j2w9CkKL._SY264_BO1,204,203,200_QL40_ML2_.jpg",
        "Price of the Product": "\u20ac11.90",
        "Product Details": "Product detailsPublisher  : Breitkopf & Hrtel (9 Aug. 1990) Language  : German Paperback  : 20 pages ISBN-10  : 000417805X ISBN-13  : 978-0004178059 Best Sellers Rank:3,582,907 in Books (See Top 100 in Books) 8,003 in Piano & Keyboards Songbooks"
    },
    {
        "ID": 87,
        "Product URL": "https://www.amazon.fr/dp/000417805X",
        "Product Title": "Choralfantasie feste burg orgue",
        "Product Image URL": "https://images-eu.ssl-images-amazon.com/images/I/418j2w9CkKL._SY291_BO1,204,203,200_QL40_ML2_.jpg",
        "Price of the Product": "(0%)",
        "Product Details": "Dtails sur le produitditeur : BREITKOPF (1 janvier 2000) Langue : Allemand Broch : 20 pages ISBN-10 : 000417805X ISBN-13 : 978-0004178059 Poids de l'article : 401 g"
    },
    {
        "ID": 88,
        "Product URL": "https://www.amazon.de/dp/000417870X",
        "Product Title": "3 St\u00fccke op. 142 f\u00fcr Orgel - 1. Stimmen der Nacht - 2. Violalse mignonne - 3. Romantisch (EB 8584)",
        "Product Image URL": "https://images-eu.ssl-images-amazon.com/images/I/51jcnDzKubL._SX198_BO1,204,203,200_QL40_ML2_.jpg",
        "Price of the Product": "\u20ac13.90",
        "Product Details": "Product detailsPublisher  : Breitkopf & Hrtel (31 Oct. 1991) Language  : German Paperback  : 24 pages ISBN-10  : 000417870X ISBN-13  : 979-0004178706 Best Sellers Rank:3,781,424 in Books (See Top 100 in Books) 8,333 in Piano & Keyboards Songbooks"
    },
    {
        "ID": 89,
        "Product URL": "https://www.amazon.fr/dp/000417870X",
        "Product Title": "Stucke(3) op.142 orgue",
        "Product Image URL": "https://images-eu.ssl-images-amazon.com/images/I/51jcnDzKubL._SX218_BO1,204,203,200_QL40_ML2_.jpg",
        "Price of the Product": "18,15\u00a0\u20ac",
        "Product Details": "Dtails sur le produitditeur : BREITKOPF (1 janvier 2000) Langue : Allemand Broch : 24 pages ISBN-10 : 000417870X ISBN-13 : 979-0004178706 Poids de l'article : 401 g"
    },
    {
        "ID": 90,
        "Product URL": "https://www.amazon.de/dp/000420736X",
        "Product Title": "L'ARLESIENNE-SUITE NR. 2 ORCHESTRE",
        "Product Image URL": "https://images-eu.ssl-images-amazon.com/images/I/41ELX18MMVL._SX198_BO1,204,203,200_QL40_ML2_.jpg",
        "Price of the Product": "(0%)",
        "Product Details": "Product detailsPublisher  : BREITKOPF (1 Jan. 2000) Language  : French ISBN-10  : 000420736X ISBN-13  : 979-0004207369"
    },
    {
        "ID": 91,
        "Product URL": "https://www.amazon.fr/dp/000420736X",
        "Product Title": "L'arlesienne-suite nr. 2 orchestre",
        "Product Image URL": "https://images-eu.ssl-images-amazon.com/images/I/41ELX18MMVL._SX218_BO1,204,203,200_QL40_ML2_.jpg",
        "Price of the Product": "(0%)",
        "Product Details": "Dtails sur le produitditeur : BREITKOPF (1 janvier 2000) Langue : Franais ISBN-10 : 000420736X ISBN-13 : 979-0004207369 Poids de l'article : 1 kg"
    },
    {
        "ID": 92,
        "Product URL": "https://www.amazon.de/dp/000421143X",
        "Product Title": "EIN DEUTSCHES REQUIEM 2 KLAV",
        "Product Image URL": "https://images-eu.ssl-images-amazon.com/images/I/41kvwEvPVpL._SX198_BO1,204,203,200_QL40_ML2_.jpg",
        "Price of the Product": "\u20ac92.00",
        "Product Details": "Product detailsPublisher  : BREITKOPF (1 Jan. 2000) Language  : French ISBN-10  : 000421143X ISBN-13  : 979-0004211434"
    },
    {
        "ID": 93,
        "Product URL": "https://www.amazon.fr/dp/000421143X",
        "Product Title": "Ein deutsches requiem 2 klav",
        "Product Image URL": "https://images-eu.ssl-images-amazon.com/images/I/41kvwEvPVpL._SX218_BO1,204,203,200_QL40_ML2_.jpg",
        "Price of the Product": "(0%)",
        "Product Details": "Dtails sur le produitditeur : BREITKOPF (1 janvier 2000) Langue : Franais ISBN-10 : 000421143X ISBN-13 : 979-0004211434 Poids de l'article : 2.4 kg"
    }
]